cntr/__init__.py
cntr/api.py
cntr/auth/__init__.py
cntr/auth/models.py
cntr/auth/security.py
cntr/auth/service.py
cntr/auth/views.py
cntr/b2b/models.py
cntr/config.py
cntr/core/__init__.py
cntr/core/celery_app.py
cntr/core/models.py
cntr/core/service.py
cntr/core/views.py
cntr/database.py
cntr/email-templates/src/new_account.mjml
cntr/email-templates/src/reset_password.mjml
cntr/email-templates/src/test_email.mjml
cntr/initial_data.py
cntr/main.py
cntr/models.py
cntr/static/frontend/.dockerignore
cntr/static/frontend/.gitignore
cntr/static/frontend/babel.config.js
cntr/static/frontend/Dockerfile
cntr/static/frontend/nginx-backend-not-found.conf
cntr/static/frontend/package-lock.json
cntr/static/frontend/package.json
cntr/static/frontend/public/favicon.ico
cntr/static/frontend/public/img/icons/android-chrome-192x192.png
cntr/static/frontend/public/img/icons/android-chrome-512x512.png
cntr/static/frontend/public/img/icons/apple-touch-icon-120x120.png
cntr/static/frontend/public/img/icons/apple-touch-icon-152x152.png
cntr/static/frontend/public/img/icons/apple-touch-icon-180x180.png
cntr/static/frontend/public/img/icons/apple-touch-icon-60x60.png
cntr/static/frontend/public/img/icons/apple-touch-icon-76x76.png
cntr/static/frontend/public/img/icons/apple-touch-icon.png
cntr/static/frontend/public/img/icons/favicon-16x16.png
cntr/static/frontend/public/img/icons/favicon-32x32.png
cntr/static/frontend/public/img/icons/msapplication-icon-144x144.png
cntr/static/frontend/public/img/icons/mstile-150x150.png
cntr/static/frontend/public/img/icons/safari-pinned-tab.svg
cntr/static/frontend/public/index.html
cntr/static/frontend/public/manifest.json
cntr/static/frontend/public/robots.txt
cntr/static/frontend/README.md
cntr/static/frontend/src/api.ts
cntr/static/frontend/src/App.vue
cntr/static/frontend/src/assets/logo.png
cntr/static/frontend/src/babel.config.js
cntr/static/frontend/src/component-hooks.ts
cntr/static/frontend/src/components/NotificationsManager.vue
cntr-0.1.0.dist-info/WHEEL
cntr-0.1.0.dist-info/METADATA
cntr-0.1.0.dist-info/RECORD
