Metadata-Version: 2.1
Name: cntr
Version: 0.1.0
Summary: ECommerce connector
Author: Ming Shen
Requires-Python: >=3.9,<4.0
Classifier: Programming Language :: Python :: 3
Classifier: Programming Language :: Python :: 3.9
Requires-Dist: Jinja2 (>=2.11.3,<3.0.0)
Requires-Dist: aiofiles (>=0.6.0,<0.7.0)
Requires-Dist: alembic (>=1.5.5,<2.0.0)
Requires-Dist: bcrypt (>=3.2.0,<4.0.0)
Requires-Dist: celery (>=5.0.5,<6.0.0)
Requires-Dist: email-validator (>=1.1.2,<2.0.0)
Requires-Dist: emails (>=0.6,<0.7)
Requires-Dist: fastapi (>=0.63.0,<0.64.0)
Requires-Dist: httpx (>=0.17.0,<0.18.0)
Requires-Dist: passlib (>=1.7.4,<2.0.0)
Requires-Dist: pydantic[dotenv] (>=1.8.1,<2.0.0)
Requires-Dist: pyodbc (>=4.0.30,<5.0.0)
Requires-Dist: python-jose (>=3.2.0,<4.0.0)
Requires-Dist: python-multipart (>=0.0.5,<0.0.6)
Requires-Dist: raven (>=6.10.0,<7.0.0)
Requires-Dist: tabulate (>=0.8.9,<0.9.0)
Requires-Dist: uvicorn (>=0.13.4,<0.14.0)
